{"response":"activePlayerOptions","playerMoves":[{"contents":{"tag":"PassTurn"},"tag":"CursedTreasurePlayerMove"},{"contents":{"contents":"LightRed","tag":"RaiseTreasure"},"tag":"CursedTreasurePlayerMove"},{"contents":{"contents":[-10,7],"tag":"MoveJeep"},"tag":"CursedTreasurePlayerMove"},{"contents":{"contents":[-9,2],"tag":"MoveJeep"},"tag":"CursedTreasurePlayerMove"},{"contents":{"contents":[-9,3],"tag":"MoveJeep"},"tag":"CursedTreasurePlayerMove"},{"contents":{"contents":[-9,4],"tag":"MoveJeep"},"tag":"CursedTreasurePlayerMove"},{"contents":{"contents":[-9,5],"tag":"MoveJeep"},"tag":"CursedTreasurePlayerMove"},{"contents":{"contents":[-9,6],"tag":"MoveJeep"},"tag":"CursedTreasurePlayerMove"},{"contents":{"contents":[-8,3],"tag":"MoveJeep"},"tag":"CursedTreasurePlayerMove"},{"contents":{"contents":[-8,4],"tag":"MoveJeep"},"tag":"CursedTreasurePlayerMove"},{"contents":{"contents":[-8,5],"tag":"MoveJeep"},"tag":"CursedTreasurePlayerMove"},{"contents":{"contents":[-7,5],"tag":"MoveJeep"},"tag":"CursedTreasurePlayerMove"}]}